{
  "project_info": {
    "project_number": "334361003105",
    "project_id": "android-2b155",
    "storage_bucket": "android-2b155.appspot.com"
  },
  "client": [
    {
      "client_info": {
        "mobilesdk_app_id": "1:334361003105:android:12373e72c699baae031620",
        "android_client_info": {
          "package_name": "com.example.museo"
        }
      },
      "oauth_client": [
        {
          "client_id": "334361003105-uieeqn2151hlauq6msovm26jsmo8akcp.apps.googleusercontent.com",
          "client_type": 3
        }
      ],
      "api_key": [
        {
          "current_key": "AIzaSyA3fgmeiiYR1rEwtR5Ab2VN5UWliPtxt9M"
        }
      ],
      "services": {
        "appinvite_service": {
          "other_platform_oauth_client": [
            {
              "client_id": "334361003105-uieeqn2151hlauq6msovm26jsmo8akcp.apps.googleusercontent.com",
              "client_type": 3
            }
          ]
        }
      }
    }
  ],
  "configuration_version": "1"
}